{
	"name": "load_transformed_yellowtaxidata",
	"properties": {
		"linkedServiceName": {
			"referenceName": "projectsynapseworkspace-WorkspaceDefaultStorage",
			"type": "LinkedServiceReference"
		},
		"annotations": [],
		"type": "Parquet",
		"typeProperties": {
			"location": {
				"type": "AzureBlobFSLocation",
				"folderPath": "TransformedData/YellowTaxi",
				"fileSystem": "projectdatalakestoragefilesystem"
			},
			"compressionCodec": "snappy"
		},
		"schema": []
	},
	"type": "Microsoft.Synapse/workspaces/datasets"
}